[[{"isTitle": true, "value": "Writing board stela of Nebseni"}, {"label": "View item details", "isLink": true, "value": "http://www.metmuseum.org/art/collection/search/544345"}, {"isImage": true, "value": "https://images.metmuseum.org/CRDImages/eg/web-large/26.3.237.JPG"}, {"label": "Object Number", "value": "26.3.237"}, {"label": "Department", "value": "Egyptian Art"}, {"label": "Accession Year", "value": "1926"}, {"label": "Country of origin", "value": "Egypt"}, {"label": "Medium", "value": "Wood, paint"}, {"label": "Dimensions", "value": "H. 57.2 cm (22 1/2 in.); W. 50 cm (19 11/16 in.); D. 3 cm (1 3/16 in.)"}, {"label": "Credit", "value": "Rogers Fund, 1926"}], [{"isTitle": true, "value": "Stela of Dedu"}, {"label": "View item details", "isLink": true, "value": "http://www.metmuseum.org/art/collection/search/544346"}, {"isImage": true, "value": "https://images.metmuseum.org/CRDImages/eg/web-large/16.10.333.jpg"}, {"label": "Object Number", "value": "16.10.333"}, {"label": "Department", "value": "Egyptian Art"}, {"label": "Accession Year", "value": "1916"}, {"label": "Country of origin", "value": "Egypt"}, {"label": "Medium", "value": "Limestone (indurated), paint"}, {"label": "Dimensions", "value": "H. 38 cm (14 15/16 in); W. 25 cm (9 13/16 in)"}, {"label": "Credit", "value": "Rogers Fund, 1916"}], [{"isTitle": true, "value": "Stela of Nakht"}, {"label": "View item details", "isLink": true, "value": "http://www.metmuseum.org/art/collection/search/544347"}, {"isImage": true, "value": "https://images.metmuseum.org/CRDImages/eg/web-large/LC-11_155_1_EGDP029179.jpg"}, {"label": "Object Number", "value": "11.155.1"}, {"label": "Department", "value": "Egyptian Art"}, {"label": "Accession Year", "value": "1911"}, {"label": "Country of origin", "value": "Egypt"}, {"label": "Medium", "value": "Limestone, paint"}, {"label": "Dimensions", "value": "H. 34.6 \u00d7 W. 25 \u00d7 D. 7.6 cm, 9.9 kg (13 5/8 \u00d7 9 13/16 \u00d7 3 in., 21.8 lb.)"}, {"label": "Credit", "value": "Gift of J. Pierpont Morgan, 1911"}], [{"isTitle": true, "value": "Stela of Rehuerdjersen"}, {"label": "View item details", "isLink": true, "value": "http://www.metmuseum.org/art/collection/search/544348"}, {"isImage": true, "value": "https://images.metmuseum.org/CRDImages/eg/web-large/EG41.jpg"}, {"label": "Object Number", "value": "12.182.1"}, {"label": "Department", "value": "Egyptian Art"}, {"label": "Accession Year", "value": "1912"}, {"label": "Country of origin", "value": "Egypt"}, {"label": "Medium", "value": "Limestone"}, {"label": "Dimensions", "value": "H. 46.1 cm (18 1/8 in.); W. 23.2 cm (9 1/8 in.); D. 10.6 cm (4 1/16 in.)"}, {"label": "Credit", "value": "Rogers Fund, 1912"}], [{"isTitle": true, "value": "Stela of Four Women"}, {"label": "View item details", "isLink": true, "value": "http://www.metmuseum.org/art/collection/search/544349"}, {"isImage": true, "value": "https://images.metmuseum.org/CRDImages/eg/web-large/LC-36_3_270_EGDP029178.jpg"}, {"label": "Object Number", "value": "36.3.270"}, {"label": "Department", "value": "Egyptian Art"}, {"label": "Accession Year", "value": "1936"}, {"label": "Country of origin", "value": "Egypt"}, {"label": "Medium", "value": "Limestone, paint"}, {"label": "Dimensions", "value": "H. 48.5 \u00d7 W. 26 \u00d7 D. 7.8 cm, 11.1 kg (19 1/8 \u00d7 10 1/4 \u00d7 3 1/16 in., 24.4 lb.)"}, {"label": "Credit", "value": "Rogers Fund, 1936"}], [{"isTitle": true, "value": "Double offering table"}, {"label": "View item details", "isLink": true, "value": "http://www.metmuseum.org/art/collection/search/544350"}, {"isImage": true, "value": "https://images.metmuseum.org/CRDImages/eg/web-large/12.181.197.JPG"}, {"label": "Object Number", "value": "12.181.197"}, {"label": "Department", "value": "Egyptian Art"}, {"label": "Accession Year", "value": "1912"}, {"label": "Country of origin", "value": "Egypt"}, {"label": "Medium", "value": "Limestone"}, {"label": "Dimensions", "value": "L. 30.5 \u00d7 W. 34 \u00d7 H. 6.5 cm, 10.9 kg (12 \u00d7 13 3/8 \u00d7 2 9/16 in., 24 lb.)"}, {"label": "Credit", "value": "Rogers Fund, 1912"}], [{"isTitle": true, "value": "Model Tile for food offerings"}, {"label": "View item details", "isLink": true, "value": "http://www.metmuseum.org/art/collection/search/544351"}, {"isImage": true, "value": "https://images.metmuseum.org/CRDImages/eg/web-large/15.3.125.jpg"}, {"label": "Object Number", "value": "15.3.125"}, {"label": "Department", "value": "Egyptian Art"}, {"label": "Accession Year", "value": "1915"}, {"label": "Country of origin", "value": "Egypt"}, {"label": "Medium", "value": "Blue faience"}, {"label": "Dimensions", "value": "h. 15 cm (5 7/8 in); w. 9.5 cm (3 3/4 in)"}, {"label": "Credit", "value": "Rogers Fund, 1915"}], [{"isTitle": true, "value": "Model cucumber"}, {"label": "View item details", "isLink": true, "value": "http://www.metmuseum.org/art/collection/search/544352"}, {"isImage": true, "value": "https://images.metmuseum.org/CRDImages/eg/web-large/15.3.130.jpg"}, {"label": "Object Number", "value": "15.3.130"}, {"label": "Department", "value": "Egyptian Art"}, {"label": "Accession Year", "value": "1915"}, {"label": "Country of origin", "value": "Egypt"}, {"label": "Medium", "value": "Faience"}, {"label": "Dimensions", "value": "l. 9.6 cm (3 3/4 in)"}, {"label": "Credit", "value": "Rogers Fund, 1915"}], [{"isTitle": true, "value": "Model cup"}, {"label": "View item details", "isLink": true, "value": "http://www.metmuseum.org/art/collection/search/544354"}, {"isImage": true, "value": "https://images.metmuseum.org/CRDImages/eg/web-large/15.3.128.jpg"}, {"label": "Object Number", "value": "15.3.128"}, {"label": "Department", "value": "Egyptian Art"}, {"label": "Accession Year", "value": "1915"}, {"label": "Country of origin", "value": "Egypt"}, {"label": "Medium", "value": "Blue faience"}, {"label": "Dimensions", "value": "h. 3.6 cm (1 7/16 in)"}, {"label": "Credit", "value": "Rogers Fund, 1915"}], [{"isTitle": true, "value": "Stela of Khonsu"}, {"label": "View item details", "isLink": true, "value": "http://www.metmuseum.org/art/collection/search/544360"}, {"isImage": true, "value": "https://images.metmuseum.org/CRDImages/eg/web-large/21.2.69_EGDP022530.jpg"}, {"label": "Object Number", "value": "21.2.69"}, {"label": "Department", "value": "Egyptian Art"}, {"label": "Accession Year", "value": "1921"}, {"label": "Country of origin", "value": "Egypt"}, {"label": "Medium", "value": "Limestone, paint"}, {"label": "Dimensions", "value": "H. 42.6 \u00d7 W. 26.5 \u00d7 D. 10.5 cm, Wt. 19.1 kg (16 3/4 \u00d7 10 7/16 \u00d7 4 1/8 in., 42 lb.)"}, {"label": "Credit", "value": "Rogers Fund, 1921"}], [{"isTitle": true, "value": "Stela of Siamun"}, {"label": "View item details", "isLink": true, "value": "http://www.metmuseum.org/art/collection/search/544363"}, {"isImage": true, "value": "https://images.metmuseum.org/CRDImages/eg/web-large/22.3.309.JPG"}, {"label": "Object Number", "value": "22.3.309"}, {"label": "Department", "value": "Egyptian Art"}, {"label": "Accession Year", "value": "1922"}, {"label": "Country of origin", "value": "Egypt"}, {"label": "Medium", "value": "Limestone, paint"}, {"label": "Dimensions", "value": "H. 26.8 cm (10 9/16 in.)"}, {"label": "Credit", "value": "Rogers Fund and Edward S. Harkness Gift, 1922"}], [{"isTitle": true, "value": "Coffin of Ikhet"}, {"label": "View item details", "isLink": true, "value": "http://www.metmuseum.org/art/collection/search/544365"}, {"isImage": true, "value": "https://images.metmuseum.org/CRDImages/eg/web-large/M6A_316.jpg"}, {"label": "Object Number", "value": "32.3.430a, b"}, {"label": "Department", "value": "Egyptian Art"}, {"label": "Accession Year", "value": "1932"}, {"label": "Country of origin", "value": "Egypt"}, {"label": "Medium", "value": "Sycomore wood"}, {"label": "Dimensions", "value": "coffin box: l. 198 cm (77 15/16 in); w. 49.5 cm (19 1/2 in); h. 60 cm (23 5/8 in)\n \n lid: l. 177 cm (69 11/16 in); w. 44 cm (17 5/16 in); h. 17 cm (6 11/16 in)"}, {"label": "Credit", "value": "Rogers Fund, 1932"}], [{"isTitle": true, "value": "Shabti of Wahneferhotep"}, {"label": "View item details", "isLink": true, "value": "http://www.metmuseum.org/art/collection/search/544366"}, {"isImage": true, "value": "https://images.metmuseum.org/CRDImages/eg/web-large/14.3.70_01.jpg"}, {"label": "Object Number", "value": "14.3.70"}, {"label": "Department", "value": "Egyptian Art"}, {"label": "Accession Year", "value": "1914"}, {"label": "Country of origin", "value": "Egypt"}, {"label": "Medium", "value": "Wood, paint, gold leaf"}, {"label": "Dimensions", "value": "H. 21 cm (8 1/4 in.); W. 6.8 cm (2 11/16 in.); D. 5.2 cm (2 1/16 in.)"}, {"label": "Credit", "value": "Rogers Fund and Edward S. Harkness Gift, 1914"}], [{"isTitle": true, "value": "Shabti coffin of Wahneferhotep"}, {"label": "View item details", "isLink": true, "value": "http://www.metmuseum.org/art/collection/search/544367"}, {"isImage": true, "value": "https://images.metmuseum.org/CRDImages/eg/web-large/DP311755.jpg"}, {"label": "Object Number", "value": "14.3.69a, b"}, {"label": "Department", "value": "Egyptian Art"}, {"label": "Accession Year", "value": "1914"}, {"label": "Country of origin", "value": "Egypt"}, {"label": "Medium", "value": "Wood, paint, gold leaf."}, {"label": "Dimensions", "value": "L. 25.1 cm (9 7/8 in.) W. 10.4 cm (4 1/8 in.) H. 15.5 cm (6 1/8 in.)"}, {"label": "Credit", "value": "Rogers Fund and Edward S. Harkness Gift, 1914"}], [{"isTitle": true, "value": "Cylinder Seal with Sekhemre-khutawi (Sebekhotep I)"}, {"label": "View item details", "isLink": true, "value": "http://www.metmuseum.org/art/collection/search/544368"}, {"isImage": true, "value": "https://images.metmuseum.org/CRDImages/eg/web-large/26.7.24Impression.jpg"}, {"label": "Object Number", "value": "26.7.24"}, {"label": "Department", "value": "Egyptian Art"}, {"label": "Accession Year", "value": "1926"}, {"label": "Country of origin", "value": "Egypt"}, {"label": "Medium", "value": "Green glazed steatite"}, {"label": "Dimensions", "value": "L. 1.6 cm (5/8 in)"}, {"label": "Credit", "value": "Purchase, Edward S. Harkness Gift, 1926"}], [{"isTitle": true, "value": "Cylinder Seal of King Amenemhat Sebekhotep"}, {"label": "View item details", "isLink": true, "value": "http://www.metmuseum.org/art/collection/search/544369"}, {"isImage": true, "value": "https://images.metmuseum.org/CRDImages/eg/web-large/LC-30_8_319_EGDP030261.jpg"}, {"label": "Object Number", "value": "30.8.319"}, {"label": "Department", "value": "Egyptian Art"}, {"label": "Accession Year", "value": "1930"}, {"label": "Country of origin", "value": "Egypt"}, {"label": "Medium", "value": "Glazed steatite"}, {"label": "Dimensions", "value": "L. 2.1 \u00d7 Dia. 0.7 cm (13/16 \u00d7 1/4 in.)"}, {"label": "Credit", "value": "Theodore M. Davis Collection, Bequest of Theodore M. Davis, 1915"}], [{"isTitle": true, "value": "Cylinder Seal of Amenemhat Senbef"}, {"label": "View item details", "isLink": true, "value": "http://www.metmuseum.org/art/collection/search/544370"}, {"isImage": true, "value": "https://images.metmuseum.org/CRDImages/eg/web-large/LC-26_7_23_EGDP030265.jpg"}, {"label": "Object Number", "value": "26.7.23"}, {"label": "Department", "value": "Egyptian Art"}, {"label": "Accession Year", "value": "1926"}, {"label": "Country of origin", "value": "Egypt"}, {"label": "Medium", "value": "Glazed steatite"}, {"label": "Dimensions", "value": "L. 4.8 \u00d7 Dia. 1.2 cm (1 7/8 \u00d7 1/2 in.)"}, {"label": "Credit", "value": "Purchase, Edward S. Harkness Gift, 1926"}], [{"isTitle": true, "value": "Bilingual Cylinder Seal"}, {"label": "View item details", "isLink": true, "value": "http://www.metmuseum.org/art/collection/search/544371"}, {"isImage": true, "value": "https://images.metmuseum.org/CRDImages/eg/web-large/26.7.21_front_view_2.jpg"}, {"label": "Object Number", "value": "26.7.21"}, {"label": "Department", "value": "Egyptian Art"}, {"label": "Accession Year", "value": "1926"}, {"label": "Country of origin", "value": "Egypt"}, {"label": "Medium", "value": "Lapis-lazuli"}, {"label": "Dimensions", "value": "h. 3.9 cm (1 9/16 in)"}, {"label": "Credit", "value": "Purchase, Edward S. Harkness Gift, 1926"}], [{"isTitle": true, "value": "Cylinder Seal of King Seankhibre Amenemhat VI"}, {"label": "View item details", "isLink": true, "value": "http://www.metmuseum.org/art/collection/search/544372"}, {"isImage": true, "value": "https://images.metmuseum.org/CRDImages/eg/web-large/LC-11_150_33_EGDP030256.jpg"}, {"label": "Object Number", "value": "11.150.33"}, {"label": "Department", "value": "Egyptian Art"}, {"label": "Accession Year", "value": "1911"}, {"label": "Country of origin", "value": "Egypt"}, {"label": "Medium", "value": "Glazed steatite"}, {"label": "Dimensions", "value": "L. 1.5 \u00d7 Dia. 0.6 cm (9/16 \u00d7 1/4 in.)"}, {"label": "Credit", "value": "Rogers Fund, 1911"}], [{"isTitle": true, "value": "Cylinder seal with the Horus name of Amenemhat VII"}, {"label": "View item details", "isLink": true, "value": "http://www.metmuseum.org/art/collection/search/544373"}, {"isImage": true, "value": "https://images.metmuseum.org/CRDImages/eg/web-large/LC-10_130_1640_EGDP030250.jpg"}, {"label": "Object Number", "value": "10.130.1640"}, {"label": "Department", "value": "Egyptian Art"}, {"label": "Accession Year", "value": "1910"}, {"label": "Country of origin", "value": "Egypt"}, {"label": "Medium", "value": "Glazed steatite"}, {"label": "Dimensions", "value": "L. 4 \u00d7 Dia. 1.2 cm (1 9/16 \u00d7 1/2 in.)"}, {"label": "Credit", "value": "Gift of Helen Miller Gould, 1910"}], [{"isTitle": true, "value": "Cylinder seal inscribed for Khaneferre Sobekhotep III"}, {"label": "View item details", "isLink": true, "value": "http://www.metmuseum.org/art/collection/search/544379"}, {"isImage": true, "value": "https://images.metmuseum.org/CRDImages/eg/web-large/LC-10_130_1638_EGDP030245.jpg"}, {"label": "Object Number", "value": "10.130.1638"}, {"label": "Department", "value": "Egyptian Art"}, {"label": "Accession Year", "value": "1910"}, {"label": "Country of origin", "value": "Egypt"}, {"label": "Medium", "value": "Glazed steatite"}, {"label": "Dimensions", "value": "L. 2.3 \u00d7 Dia. 1 cm (7/8 \u00d7 3/8 in.)"}, {"label": "Credit", "value": "Gift of Helen Miller Gould, 1910"}], [{"isTitle": true, "value": "Cylinder Seal of King Merneferre Aya"}, {"label": "View item details", "isLink": true, "value": "http://www.metmuseum.org/art/collection/search/544388"}, {"isImage": true, "value": "https://images.metmuseum.org/CRDImages/eg/web-large/LC-10_130_1639_EGDP030251.jpg"}, {"label": "Object Number", "value": "10.130.1639"}, {"label": "Department", "value": "Egyptian Art"}, {"label": "Accession Year", "value": "1910"}, {"label": "Country of origin", "value": "Egypt"}, {"label": "Medium", "value": "Glazed steatite"}, {"label": "Dimensions", "value": "L.1.3 \u00d7 Dia. 0.4 cm (1/2 \u00d7 3/16 in.)"}, {"label": "Credit", "value": "Gift of Helen Miller Gould, 1910"}], [{"isTitle": true, "value": "Seal"}, {"label": "View item details", "isLink": true, "value": "http://www.metmuseum.org/art/collection/search/544400"}, {"isImage": true, "value": "https://images.metmuseum.org/CRDImages/eg/web-large/10.130.983.jpg"}, {"label": "Object Number", "value": "10.130.983"}, {"label": "Department", "value": "Egyptian Art"}, {"label": "Accession Year", "value": "1910"}, {"label": "Country of origin", "value": "Egypt"}, {"label": "Medium", "value": "Jasper"}, {"label": "Dimensions", "value": "1 1/8 x 1 5/8 in. (2.8 x 4.2 cm)"}, {"label": "Credit", "value": "Gift of Helen Miller Gould, 1910"}], [{"isTitle": true, "value": "Stamp Seal Inscribed With An Ankh Between Two Falcons"}, {"label": "View item details", "isLink": true, "value": "http://www.metmuseum.org/art/collection/search/544401"}, {"isImage": true, "value": "https://images.metmuseum.org/CRDImages/eg/web-large/26-7-41.jpg"}, {"label": "Object Number", "value": "26.7.41"}, {"label": "Department", "value": "Egyptian Art"}, {"label": "Accession Year", "value": "1926"}, {"label": "Country of origin", "value": "Egypt"}, {"label": "Medium", "value": "Steatite"}, {"label": "Dimensions", "value": "h. 1.7 cm (11/16 in); w. 2.2 cm (7/8 in)"}, {"label": "Credit", "value": "Purchase, Edward S. Harkness Gift, 1926"}], [{"isTitle": true, "value": "Pyramid-Shaped Stamp Seal Inscribed With A Labyrinth Design"}, {"label": "View item details", "isLink": true, "value": "http://www.metmuseum.org/art/collection/search/544402"}, {"isImage": true, "value": "https://images.metmuseum.org/CRDImages/eg/web-large/26.7.42Impression.jpg"}, {"label": "Object Number", "value": "26.7.42"}, {"label": "Department", "value": "Egyptian Art"}, {"label": "Accession Year", "value": "1926"}, {"label": "Country of origin", "value": "Egypt"}, {"label": "Medium", "value": "Brown limestone, Indurated"}, {"label": "Dimensions", "value": "h. 2.7 cm (1 1/16 in); w. 3.8 cm (1 1/2 in)"}, {"label": "Credit", "value": "Purchase, Edward S. Harkness Gift, 1926"}], [{"isTitle": true, "value": "Hippopotamus-Head Design Amulet Inscribed With Four Linked Ibex Heads."}, {"label": "View item details", "isLink": true, "value": "http://www.metmuseum.org/art/collection/search/544409"}, {"isImage": true, "value": "https://images.metmuseum.org/CRDImages/eg/web-large/26.7.39_EGDP021758.jpg"}, {"label": "Object Number", "value": "26.7.39"}, {"label": "Department", "value": "Egyptian Art"}, {"label": "Accession Year", "value": "1926"}, {"label": "Country of origin", "value": "Egypt"}, {"label": "Medium", "value": "Steatite, white glazed"}, {"label": "Dimensions", "value": "diam. 2.8 cm (1 1/8 in)"}, {"label": "Credit", "value": "Purchase, Edward S. Harkness Gift, 1926"}], [{"isTitle": true, "value": "Motto Clasp of Sithathoryunet"}, {"label": "View item details", "isLink": true, "value": "http://www.metmuseum.org/art/collection/search/544414"}, {"isImage": true, "value": "https://images.metmuseum.org/CRDImages/eg/web-large/16.1.16_front.JPG"}, {"label": "Object Number", "value": "16.1.16"}, {"label": "Department", "value": "Egyptian Art"}, {"label": "Accession Year", "value": "1916"}, {"label": "Country of origin", "value": "Egypt"}, {"label": "Medium", "value": "Gold, carnelian, paste"}, {"label": "Dimensions", "value": "H. 1.5 cm (9/16 in); W. 1.4 cm (9/16 in)"}, {"label": "Credit", "value": "Purchase, Rogers Fund and Henry Walters Gift, 1916"}], [{"isTitle": true, "value": "Motto Clasp of Sithathoryunet"}, {"label": "View item details", "isLink": true, "value": "http://www.metmuseum.org/art/collection/search/544415"}, {"isImage": true, "value": "https://images.metmuseum.org/CRDImages/eg/web-large/16.1.17_front.JPG"}, {"label": "Object Number", "value": "16.1.17"}, {"label": "Department", "value": "Egyptian Art"}, {"label": "Accession Year", "value": "1916"}, {"label": "Country of origin", "value": "Egypt"}, {"label": "Medium", "value": "Gold, carnelian, paste"}, {"label": "Dimensions", "value": "H. 2 \u00d7 W. 2.1 cm (13/16 \u00d7 13/16 in.)"}, {"label": "Credit", "value": "Purchase, Rogers Fund and Henry Walters Gift, 1916"}], [{"isTitle": true, "value": "Motto Clasp of Sithathoryunet"}, {"label": "View item details", "isLink": true, "value": "http://www.metmuseum.org/art/collection/search/544416"}, {"isImage": true, "value": "https://images.metmuseum.org/CRDImages/eg/web-large/16.1.18_front.JPG"}, {"label": "Object Number", "value": "16.1.18"}, {"label": "Department", "value": "Egyptian Art"}, {"label": "Accession Year", "value": "1916"}, {"label": "Country of origin", "value": "Egypt"}, {"label": "Medium", "value": "Gold, carnelian, paste"}, {"label": "Dimensions", "value": "H. 2.3 \u00d7 W. 1.9 cm (7/8 \u00d7 3/4 in.)"}, {"label": "Credit", "value": "Purchase, Rogers Fund and Henry Walters Gift, 1916"}], [{"isTitle": true, "value": "Motto Clasp of Sithathoryunet"}, {"label": "View item details", "isLink": true, "value": "http://www.metmuseum.org/art/collection/search/544417"}, {"isImage": true, "value": "https://images.metmuseum.org/CRDImages/eg/web-large/16.1.19_front.JPG"}, {"label": "Object Number", "value": "16.1.19"}, {"label": "Department", "value": "Egyptian Art"}, {"label": "Accession Year", "value": "1916"}, {"label": "Country of origin", "value": "Egypt"}, {"label": "Medium", "value": "Gold, carnelian, paste"}, {"label": "Dimensions", "value": "h. 1.7 cm (11/16 in); w. 1.8 cm (11/16 in)"}, {"label": "Credit", "value": "Purchase, Rogers Fund and Henry Walters Gift, 1916"}], [{"isTitle": true, "value": "Motto Clasp of Sithathoryunet"}, {"label": "View item details", "isLink": true, "value": "http://www.metmuseum.org/art/collection/search/544418"}, {"isImage": true, "value": "https://images.metmuseum.org/CRDImages/eg/web-large/16.1.20_front.JPG"}, {"label": "Object Number", "value": "16.1.20"}, {"label": "Department", "value": "Egyptian Art"}, {"label": "Accession Year", "value": "1916"}, {"label": "Country of origin", "value": "Egypt"}, {"label": "Medium", "value": "Gold, carnelian, paste"}, {"label": "Dimensions", "value": "H. 1.2 \u00d7 W. 1.3 cm (1/2 \u00d7 1/2 in.)"}, {"label": "Credit", "value": "Purchase, Rogers Fund and Henry Walters Gift, 1916"}], [{"isTitle": true, "value": "Bead Necklace"}, {"label": "View item details", "isLink": true, "value": "http://www.metmuseum.org/art/collection/search/544419"}, {"isImage": true, "value": "https://images.metmuseum.org/CRDImages/eg/web-large/13.180.12_Binder01-01-01.jpg"}, {"label": "Object Number", "value": "13.180.12"}, {"label": "Department", "value": "Egyptian Art"}, {"label": "Accession Year", "value": "1913"}, {"label": "Country of origin", "value": "Egypt"}, {"label": "Medium", "value": "Amethyst"}, {"label": "Dimensions", "value": "L. 64.5 cm (25 3/8 in.)"}, {"label": "Credit", "value": "Rogers Fund and Edward S. Harkness Gift, 1913"}], [{"isTitle": true, "value": "Girdle with Cowrie Shells"}, {"label": "View item details", "isLink": true, "value": "http://www.metmuseum.org/art/collection/search/544420"}, {"isImage": true, "value": "https://images.metmuseum.org/CRDImages/eg/web-large/DP-13694-001.jpg"}, {"label": "Object Number", "value": "13.180.11"}, {"label": "Department", "value": "Egyptian Art"}, {"label": "Accession Year", "value": "1913"}, {"label": "Country of origin", "value": "Egypt"}, {"label": "Medium", "value": "Electrum over plaster, carnelian, amethyst"}, {"label": "Dimensions", "value": "L. 66 cm (26 in.); (L. of shells): 2.5 cm (1 in.)"}, {"label": "Credit", "value": "Rogers Fund and Edward S. Harkness Gift, 1913"}], [{"isTitle": true, "value": "String of amulets and ring beads"}, {"label": "View item details", "isLink": true, "value": "http://www.metmuseum.org/art/collection/search/544421"}, {"isImage": true, "value": "https://images.metmuseum.org/CRDImages/eg/web-large/13.180.5AB_Binder01-01-08.jpg"}, {"label": "Object Number", "value": "13.180.5a, b"}, {"label": "Department", "value": "Egyptian Art"}, {"label": "Accession Year", "value": "1913"}, {"label": "Country of origin", "value": "Egypt"}, {"label": "Medium", "value": "Carnelian, amethyst, lapis lazuli, turquoise, faience, silver"}, {"label": "Dimensions", "value": "L. as restrung 22 cm (8 11/16 in.)"}, {"label": "Credit", "value": "Rogers Fund and Edward S. Harkness Gift, 1913"}], [{"isTitle": true, "value": "Falcon wearing a Double Crown"}, {"label": "View item details", "isLink": true, "value": "http://www.metmuseum.org/art/collection/search/544422"}, {"isImage": true, "value": "https://images.metmuseum.org/CRDImages/eg/web-large/DP-13693-001.jpg"}, {"label": "Object Number", "value": "13.180.2"}, {"label": "Department", "value": "Egyptian Art"}, {"label": "Accession Year", "value": "1913"}, {"label": "Country of origin", "value": "Egypt"}, {"label": "Medium", "value": "Electrum over plaster"}, {"label": "Dimensions", "value": "H. 8.7 \u00d7 W. 5.6 \u00d7 Th. 0.5 cm (3 7/16 \u00d7 2 3/16 \u00d7 3/16 in.)"}, {"label": "Credit", "value": "Rogers Fund and Edward S. Harkness Gift, 1913"}], [{"isTitle": true, "value": "Cowroid Seal Amulet with the Name of the Hyksos King Apophis"}, {"label": "View item details", "isLink": true, "value": "http://www.metmuseum.org/art/collection/search/544428"}, {"isImage": true, "value": "https://images.metmuseum.org/CRDImages/eg/web-large/c_267_bottom.jpg"}, {"label": "Object Number", "value": "26.7.267"}, {"label": "Department", "value": "Egyptian Art"}, {"label": "Accession Year", "value": "1926"}, {"label": "Country of origin", "value": "Egypt"}, {"label": "Medium", "value": "Steatite, white glaze"}, {"label": "Dimensions", "value": "l.1.7 cm (11/16 in)"}, {"label": "Credit", "value": "Purchase, Edward S. Harkness Gift, 1926"}], [{"isTitle": true, "value": "Sphinx of Hatshepsut"}, {"label": "View item details", "isLink": true, "value": "http://www.metmuseum.org/art/collection/search/544442"}, {"isImage": true, "value": "https://images.metmuseum.org/CRDImages/eg/web-large/21V_CAT088R6.jpg"}, {"label": "Object Number", "value": "31.3.166"}, {"label": "Department", "value": "Egyptian Art"}, {"label": "Accession Year", "value": "1931"}, {"label": "Country of origin", "value": "Egypt"}, {"label": "Medium", "value": "Granite, paint"}, {"label": "Dimensions", "value": "H: 164 cm (64 9/16 in.); L: 343 cm (135 1/16 in.); Wt: 6758.6 kg (14900 lb.)"}, {"label": "Credit", "value": "Rogers Fund, 1931"}]]