[[{"isTitle": true, "value": "Stucco Fragment"}, {"label": "View item details", "isLink": true, "value": "http://www.metmuseum.org/art/collection/search/741303"}, {"isImage": true, "value": "https://images.metmuseum.org/CRDImages/is/web-large/LC-N1487-front.jpg"}, {"label": "Object Number", "value": "48.101.1789"}, {"label": "Department", "value": "Islamic Art"}, {"label": "Accession Year", "value": "1948"}, {"label": "Country of origin", "value": "Iran"}, {"label": "Medium", "value": "Stucco; carved, painted"}, {"label": "Dimensions", "value": "L 4x W2 x H1.5"}, {"label": "Classification", "value": "Stucco"}, {"label": "Credit", "value": "Rogers Fund, 1948"}], [{"isTitle": true, "value": "Stucco Fragment"}, {"label": "View item details", "isLink": true, "value": "http://www.metmuseum.org/art/collection/search/741304"}, {"isImage": true, "value": "https://images.metmuseum.org/CRDImages/is/web-large/LC-N1488-front.jpg"}, {"label": "Object Number", "value": "48.101.1790"}, {"label": "Department", "value": "Islamic Art"}, {"label": "Accession Year", "value": "1948"}, {"label": "Country of origin", "value": "Iran"}, {"label": "Medium", "value": "Stucco; carved, painted"}, {"label": "Dimensions", "value": "L 6x W 3x H2"}, {"label": "Classification", "value": "Stucco"}, {"label": "Credit", "value": "Rogers Fund, 1948"}], [{"isTitle": true, "value": "Stucco Fragment"}, {"label": "View item details", "isLink": true, "value": "http://www.metmuseum.org/art/collection/search/741305"}, {"isImage": true, "value": "https://images.metmuseum.org/CRDImages/is/web-large/LC-N1489-front.jpg"}, {"label": "Object Number", "value": "48.101.1791"}, {"label": "Department", "value": "Islamic Art"}, {"label": "Accession Year", "value": "1948"}, {"label": "Country of origin", "value": "Iran"}, {"label": "Medium", "value": "Stucco; carved, painted"}, {"label": "Dimensions", "value": "L 5x W3.5 x H2"}, {"label": "Classification", "value": "Stucco"}, {"label": "Credit", "value": "Rogers Fund, 1948"}], [{"isTitle": true, "value": "Stucco Fragment"}, {"label": "View item details", "isLink": true, "value": "http://www.metmuseum.org/art/collection/search/741306"}, {"isImage": true, "value": "https://images.metmuseum.org/CRDImages/is/web-large/LC-N149-front.jpg"}, {"label": "Object Number", "value": "48.101.451"}, {"label": "Department", "value": "Islamic Art"}, {"label": "Accession Year", "value": "1948"}, {"label": "Country of origin", "value": "Iran"}, {"label": "Medium", "value": "Stucco; carved"}, {"label": "Dimensions", "value": "L. (8 cm)\n \n W. (6 cm)\n \n D. (2.5 cm)\n \n Wt."}, {"label": "Classification", "value": "Stucco"}, {"label": "Credit", "value": "Rogers Fund, 1948"}], [{"isTitle": true, "value": "Stucco Fragment"}, {"label": "View item details", "isLink": true, "value": "http://www.metmuseum.org/art/collection/search/741307"}, {"isImage": true, "value": "https://images.metmuseum.org/CRDImages/is/web-large/LC-N1490-front.jpg"}, {"label": "Object Number", "value": "48.101.1792"}, {"label": "Department", "value": "Islamic Art"}, {"label": "Accession Year", "value": "1948"}, {"label": "Country of origin", "value": "Iran"}, {"label": "Medium", "value": "Stucco; carved, painted"}, {"label": "Dimensions", "value": "L 6x W4.5 x H2.5"}, {"label": "Classification", "value": "Stucco"}, {"label": "Credit", "value": "Rogers Fund, 1948"}], [{"isTitle": true, "value": "Stucco Fragment"}, {"label": "View item details", "isLink": true, "value": "http://www.metmuseum.org/art/collection/search/741308"}, {"isImage": true, "value": "https://images.metmuseum.org/CRDImages/is/web-large/LC-N1491-front.jpg"}, {"label": "Object Number", "value": "48.101.1793"}, {"label": "Department", "value": "Islamic Art"}, {"label": "Accession Year", "value": "1948"}, {"label": "Country of origin", "value": "Iran"}, {"label": "Medium", "value": "Stucco; carved, painted"}, {"label": "Dimensions", "value": "L 5x W 4x H1.5"}, {"label": "Classification", "value": "Stucco"}, {"label": "Credit", "value": "Rogers Fund, 1948"}], [{"isTitle": true, "value": "Stucco Fragment"}, {"label": "View item details", "isLink": true, "value": "http://www.metmuseum.org/art/collection/search/741309"}, {"isImage": true, "value": "https://images.metmuseum.org/CRDImages/is/web-large/LC-N1492-front.jpg"}, {"label": "Object Number", "value": "48.101.1794"}, {"label": "Department", "value": "Islamic Art"}, {"label": "Accession Year", "value": "1948"}, {"label": "Country of origin", "value": "Iran"}, {"label": "Medium", "value": "Stucco; carved, painted"}, {"label": "Dimensions", "value": "L 5x W 3.5x H 2.5"}, {"label": "Classification", "value": "Stucco"}, {"label": "Credit", "value": "Rogers Fund, 1948"}], [{"isTitle": true, "value": "Stucco Fragment"}, {"label": "View item details", "isLink": true, "value": "http://www.metmuseum.org/art/collection/search/741310"}, {"isImage": true, "value": "https://images.metmuseum.org/CRDImages/is/web-large/LC-N1493-front.jpg"}, {"label": "Object Number", "value": "48.101.1795"}, {"label": "Department", "value": "Islamic Art"}, {"label": "Accession Year", "value": "1948"}, {"label": "Country of origin", "value": "Iran"}, {"label": "Medium", "value": "Stucco; carved, painted"}, {"label": "Dimensions", "value": "L 8x W6.5 x H 2.5"}, {"label": "Classification", "value": "Stucco"}, {"label": "Credit", "value": "Rogers Fund, 1948"}], [{"isTitle": true, "value": "Stucco Fragment"}, {"label": "View item details", "isLink": true, "value": "http://www.metmuseum.org/art/collection/search/741311"}, {"isImage": true, "value": "https://images.metmuseum.org/CRDImages/is/web-large/LC-N1494-front.jpg"}, {"label": "Object Number", "value": "48.101.1796"}, {"label": "Department", "value": "Islamic Art"}, {"label": "Accession Year", "value": "1948"}, {"label": "Country of origin", "value": "Iran"}, {"label": "Medium", "value": "Stucco; carved, painted"}, {"label": "Dimensions", "value": "L 5.5x W 4.5x H 2.5"}, {"label": "Classification", "value": "Stucco"}, {"label": "Credit", "value": "Rogers Fund, 1948"}], [{"isTitle": true, "value": "Stucco Fragment"}, {"label": "View item details", "isLink": true, "value": "http://www.metmuseum.org/art/collection/search/741312"}, {"isImage": true, "value": "https://images.metmuseum.org/CRDImages/is/web-large/LC-N1495-front.jpg"}, {"label": "Object Number", "value": "48.101.1797"}, {"label": "Department", "value": "Islamic Art"}, {"label": "Accession Year", "value": "1948"}, {"label": "Country of origin", "value": "Iran"}, {"label": "Medium", "value": "Stucco; carved, painted"}, {"label": "Dimensions", "value": "L 5x W 4x H2.5"}, {"label": "Classification", "value": "Stucco"}, {"label": "Credit", "value": "Rogers Fund, 1948"}], [{"isTitle": true, "value": "Stucco Fragment"}, {"label": "View item details", "isLink": true, "value": "http://www.metmuseum.org/art/collection/search/741313"}, {"isImage": true, "value": "https://images.metmuseum.org/CRDImages/is/web-large/LC-N1496-front.jpg"}, {"label": "Object Number", "value": "48.101.1798"}, {"label": "Department", "value": "Islamic Art"}, {"label": "Accession Year", "value": "1948"}, {"label": "Country of origin", "value": "Iran"}, {"label": "Medium", "value": "Stucco; carved, painted"}, {"label": "Dimensions", "value": "L3.5 x W3 x H 1.5"}, {"label": "Classification", "value": "Stucco"}, {"label": "Credit", "value": "Rogers Fund, 1948"}], [{"isTitle": true, "value": "Stucco Fragment"}, {"label": "View item details", "isLink": true, "value": "http://www.metmuseum.org/art/collection/search/741314"}, {"isImage": true, "value": "https://images.metmuseum.org/CRDImages/is/web-large/LC-N1497-front.jpg"}, {"label": "Object Number", "value": "48.101.1799"}, {"label": "Department", "value": "Islamic Art"}, {"label": "Accession Year", "value": "1948"}, {"label": "Country of origin", "value": "Iran"}, {"label": "Medium", "value": "Stucco; carved, painted"}, {"label": "Dimensions", "value": "L 4x W 2x H2"}, {"label": "Classification", "value": "Stucco"}, {"label": "Credit", "value": "Rogers Fund, 1948"}], [{"isTitle": true, "value": "Stucco Fragment"}, {"label": "View item details", "isLink": true, "value": "http://www.metmuseum.org/art/collection/search/741315"}, {"isImage": true, "value": "https://images.metmuseum.org/CRDImages/is/web-large/LC-N1498-front.jpg"}, {"label": "Object Number", "value": "48.101.1800"}, {"label": "Department", "value": "Islamic Art"}, {"label": "Accession Year", "value": "1948"}, {"label": "Country of origin", "value": "Iran"}, {"label": "Medium", "value": "Stucco; carved, painted"}, {"label": "Dimensions", "value": "L 4x W 3x H 3.5"}, {"label": "Classification", "value": "Stucco"}, {"label": "Credit", "value": "Rogers Fund, 1948"}], [{"isTitle": true, "value": "Stucco Fragment"}, {"label": "View item details", "isLink": true, "value": "http://www.metmuseum.org/art/collection/search/741316"}, {"isImage": true, "value": "https://images.metmuseum.org/CRDImages/is/web-large/LC-N1499-front.jpg"}, {"label": "Object Number", "value": "48.101.1801"}, {"label": "Department", "value": "Islamic Art"}, {"label": "Accession Year", "value": "1948"}, {"label": "Country of origin", "value": "Iran"}, {"label": "Medium", "value": "Stucco; carved, painted"}, {"label": "Dimensions", "value": "L 3.5x W 2x H 2.5"}, {"label": "Classification", "value": "Stucco"}, {"label": "Credit", "value": "Rogers Fund, 1948"}], [{"isTitle": true, "value": "Stucco Fragment"}, {"label": "View item details", "isLink": true, "value": "http://www.metmuseum.org/art/collection/search/741317"}, {"isImage": true, "value": "https://images.metmuseum.org/CRDImages/is/web-large/LC-N150-front.jpg"}, {"label": "Object Number", "value": "48.101.452"}, {"label": "Department", "value": "Islamic Art"}, {"label": "Accession Year", "value": "1948"}, {"label": "Country of origin", "value": "Iran"}, {"label": "Medium", "value": "Stucco; carved, painted"}, {"label": "Dimensions", "value": "L. (7 cm)\n \n W. (4 cm)\n \n D. (2.4 cm)\n \n Wt."}, {"label": "Classification", "value": "Stucco"}, {"label": "Credit", "value": "Rogers Fund, 1948"}], [{"isTitle": true, "value": "Stucco Fragment"}, {"label": "View item details", "isLink": true, "value": "http://www.metmuseum.org/art/collection/search/741318"}, {"isImage": true, "value": "https://images.metmuseum.org/CRDImages/is/web-large/LC-N1500-back.jpg"}, {"label": "Object Number", "value": "48.101.1802"}, {"label": "Department", "value": "Islamic Art"}, {"label": "Accession Year", "value": "1948"}, {"label": "Country of origin", "value": "Iran"}, {"label": "Medium", "value": "Stucco; carved, painted"}, {"label": "Dimensions", "value": "L 2.5 x W 2 x H 2"}, {"label": "Classification", "value": "Stucco"}, {"label": "Credit", "value": "Rogers Fund, 1948"}], [{"isTitle": true, "value": "Stucco Fragment"}, {"label": "View item details", "isLink": true, "value": "http://www.metmuseum.org/art/collection/search/741319"}, {"isImage": true, "value": "https://images.metmuseum.org/CRDImages/is/web-large/LC-N1501-back.jpg"}, {"label": "Object Number", "value": "48.101.1803"}, {"label": "Department", "value": "Islamic Art"}, {"label": "Accession Year", "value": "1948"}, {"label": "Country of origin", "value": "Iran"}, {"label": "Medium", "value": "Stucco; carved, painted"}, {"label": "Dimensions", "value": "L 3.5x W 2.5 x H 2"}, {"label": "Classification", "value": "Stucco"}, {"label": "Credit", "value": "Rogers Fund, 1948"}], [{"isTitle": true, "value": "Stucco Fragment"}, {"label": "View item details", "isLink": true, "value": "http://www.metmuseum.org/art/collection/search/741320"}, {"isImage": true, "value": "https://images.metmuseum.org/CRDImages/is/web-large/LC-N1502-back.jpg"}, {"label": "Object Number", "value": "48.101.1804"}, {"label": "Department", "value": "Islamic Art"}, {"label": "Accession Year", "value": "1948"}, {"label": "Country of origin", "value": "Iran"}, {"label": "Medium", "value": "Stucco; carved, painted"}, {"label": "Dimensions", "value": "L 3.5x W 2.5x H 1"}, {"label": "Classification", "value": "Stucco"}, {"label": "Credit", "value": "Rogers Fund, 1948"}], [{"isTitle": true, "value": "Stucco Fragment"}, {"label": "View item details", "isLink": true, "value": "http://www.metmuseum.org/art/collection/search/741321"}, {"isImage": true, "value": "https://images.metmuseum.org/CRDImages/is/web-large/LC-N1503-back.jpg"}, {"label": "Object Number", "value": "48.101.1805"}, {"label": "Department", "value": "Islamic Art"}, {"label": "Accession Year", "value": "1948"}, {"label": "Country of origin", "value": "Iran"}, {"label": "Medium", "value": "Stucco; carved, painted"}, {"label": "Dimensions", "value": "L7 x W6 x H 2"}, {"label": "Classification", "value": "Stucco"}, {"label": "Credit", "value": "Rogers Fund, 1948"}], [{"isTitle": true, "value": "Stucco Fragment"}, {"label": "View item details", "isLink": true, "value": "http://www.metmuseum.org/art/collection/search/741322"}, {"isImage": true, "value": "https://images.metmuseum.org/CRDImages/is/web-large/LC-N1504-back.jpg"}, {"label": "Object Number", "value": "48.101.1806"}, {"label": "Department", "value": "Islamic Art"}, {"label": "Accession Year", "value": "1948"}, {"label": "Country of origin", "value": "Iran"}, {"label": "Medium", "value": "Stucco (mortar); carved, painted"}, {"label": "Dimensions", "value": "L 6.5x W 6x H1.5"}, {"label": "Classification", "value": "Stucco"}, {"label": "Credit", "value": "Rogers Fund, 1948"}], [{"isTitle": true, "value": "Stucco Fragment"}, {"label": "View item details", "isLink": true, "value": "http://www.metmuseum.org/art/collection/search/741323"}, {"isImage": true, "value": "https://images.metmuseum.org/CRDImages/is/web-large/LC-N1505-back.jpg"}, {"label": "Object Number", "value": "48.101.1807"}, {"label": "Department", "value": "Islamic Art"}, {"label": "Accession Year", "value": "1948"}, {"label": "Country of origin", "value": "Iran"}, {"label": "Medium", "value": "Stucco; carved, painted"}, {"label": "Dimensions", "value": "L 14.5x W 6 x H 3"}, {"label": "Classification", "value": "Stucco"}, {"label": "Credit", "value": "Rogers Fund, 1948"}], [{"isTitle": true, "value": "Stucco Fragment"}, {"label": "View item details", "isLink": true, "value": "http://www.metmuseum.org/art/collection/search/741324"}, {"isImage": true, "value": "https://images.metmuseum.org/CRDImages/is/web-large/LC-N1506-back.jpg"}, {"label": "Object Number", "value": "48.101.1808"}, {"label": "Department", "value": "Islamic Art"}, {"label": "Accession Year", "value": "1948"}, {"label": "Country of origin", "value": "Iran"}, {"label": "Medium", "value": "Stucco; carved, painted"}, {"label": "Dimensions", "value": "L 5 x W 3.5 x H 1.5"}, {"label": "Classification", "value": "Stucco"}, {"label": "Credit", "value": "Rogers Fund, 1948"}], [{"isTitle": true, "value": "Stucco Fragment"}, {"label": "View item details", "isLink": true, "value": "http://www.metmuseum.org/art/collection/search/741325"}, {"isImage": true, "value": "https://images.metmuseum.org/CRDImages/is/web-large/LC-N1507-back.jpg"}, {"label": "Object Number", "value": "48.101.1809"}, {"label": "Department", "value": "Islamic Art"}, {"label": "Accession Year", "value": "1948"}, {"label": "Country of origin", "value": "Iran"}, {"label": "Medium", "value": "Stucco; carved, painted"}, {"label": "Dimensions", "value": "L 1 x W 1 x H 1 to L 3 x W 3 x H 1.5"}, {"label": "Classification", "value": "Stucco"}, {"label": "Credit", "value": "Rogers Fund, 1948"}], [{"isTitle": true, "value": "Stucco Fragment"}, {"label": "View item details", "isLink": true, "value": "http://www.metmuseum.org/art/collection/search/741326"}, {"isImage": true, "value": "https://images.metmuseum.org/CRDImages/is/web-large/LC-N1508-back.jpg"}, {"label": "Object Number", "value": "48.101.1810"}, {"label": "Department", "value": "Islamic Art"}, {"label": "Accession Year", "value": "1948"}, {"label": "Country of origin", "value": "Iran"}, {"label": "Medium", "value": "Stucco; carved, painted"}, {"label": "Dimensions", "value": "L 8.5 x W 5 x H 1.5"}, {"label": "Classification", "value": "Stucco"}, {"label": "Credit", "value": "Rogers Fund, 1948"}], [{"isTitle": true, "value": "Stucco Fragment"}, {"label": "View item details", "isLink": true, "value": "http://www.metmuseum.org/art/collection/search/741327"}, {"isImage": true, "value": "https://images.metmuseum.org/CRDImages/is/web-large/LC-N1509-back.jpg"}, {"label": "Object Number", "value": "48.101.1811"}, {"label": "Department", "value": "Islamic Art"}, {"label": "Accession Year", "value": "1948"}, {"label": "Country of origin", "value": "Iran"}, {"label": "Medium", "value": "Stucco; carved, painted"}, {"label": "Dimensions", "value": "L 4 x W 3 x H 2"}, {"label": "Classification", "value": "Stucco"}, {"label": "Credit", "value": "Rogers Fund, 1948"}], [{"isTitle": true, "value": "Stucco Fragment"}, {"label": "View item details", "isLink": true, "value": "http://www.metmuseum.org/art/collection/search/741328"}, {"isImage": true, "value": "https://images.metmuseum.org/CRDImages/is/web-large/LC-N151-front.jpg"}, {"label": "Object Number", "value": "48.101.453"}, {"label": "Department", "value": "Islamic Art"}, {"label": "Accession Year", "value": "1948"}, {"label": "Country of origin", "value": "Iran"}, {"label": "Medium", "value": "Stucco; carved, painted"}, {"label": "Dimensions", "value": "L. (7 cm)\n \n W. (4 cm)\n \n D. (3 cm)\n \n Wt."}, {"label": "Classification", "value": "Stucco"}, {"label": "Credit", "value": "Rogers Fund, 1948"}], [{"isTitle": true, "value": "Stucco Fragment"}, {"label": "View item details", "isLink": true, "value": "http://www.metmuseum.org/art/collection/search/741329"}, {"isImage": true, "value": "https://images.metmuseum.org/CRDImages/is/web-large/LC-N1510-back.jpg"}, {"label": "Object Number", "value": "48.101.1812"}, {"label": "Department", "value": "Islamic Art"}, {"label": "Accession Year", "value": "1948"}, {"label": "Country of origin", "value": "Iran"}, {"label": "Medium", "value": "Stucco; carved, painted"}, {"label": "Dimensions", "value": "L 5.5 x W 4 x H 2"}, {"label": "Classification", "value": "Stucco"}, {"label": "Credit", "value": "Rogers Fund, 1948"}], [{"isTitle": true, "value": "Stucco Fragment"}, {"label": "View item details", "isLink": true, "value": "http://www.metmuseum.org/art/collection/search/741330"}, {"isImage": true, "value": "https://images.metmuseum.org/CRDImages/is/web-large/LC-N1511-back.jpg"}, {"label": "Object Number", "value": "48.101.1813"}, {"label": "Department", "value": "Islamic Art"}, {"label": "Accession Year", "value": "1948"}, {"label": "Country of origin", "value": "Iran"}, {"label": "Medium", "value": "Stucco; carved, painted"}, {"label": "Dimensions", "value": "L 5 x W 3 x H 1"}, {"label": "Classification", "value": "Stucco"}, {"label": "Credit", "value": "Rogers Fund, 1948"}], [{"isTitle": true, "value": "Stucco Fragment"}, {"label": "View item details", "isLink": true, "value": "http://www.metmuseum.org/art/collection/search/741331"}, {"isImage": true, "value": "https://images.metmuseum.org/CRDImages/is/web-large/LC-N1512-back.jpg"}, {"label": "Object Number", "value": "48.101.1814"}, {"label": "Department", "value": "Islamic Art"}, {"label": "Accession Year", "value": "1948"}, {"label": "Country of origin", "value": "Iran"}, {"label": "Medium", "value": "Stucco; carved, painted"}, {"label": "Dimensions", "value": "L 5 x W 4 x H 3"}, {"label": "Classification", "value": "Stucco"}, {"label": "Credit", "value": "Rogers Fund, 1948"}], [{"isTitle": true, "value": "Stucco Fragment"}, {"label": "View item details", "isLink": true, "value": "http://www.metmuseum.org/art/collection/search/741332"}, {"isImage": true, "value": "https://images.metmuseum.org/CRDImages/is/web-large/LC-N1513-back.jpg"}, {"label": "Object Number", "value": "48.101.1815"}, {"label": "Department", "value": "Islamic Art"}, {"label": "Accession Year", "value": "1948"}, {"label": "Country of origin", "value": "Iran"}, {"label": "Medium", "value": "Stucco; carved, painted"}, {"label": "Dimensions", "value": "L 6 x W 3 x H 2"}, {"label": "Classification", "value": "Stucco"}, {"label": "Credit", "value": "Rogers Fund, 1948"}], [{"isTitle": true, "value": "Stucco Fragment"}, {"label": "View item details", "isLink": true, "value": "http://www.metmuseum.org/art/collection/search/741333"}, {"isImage": true, "value": "https://images.metmuseum.org/CRDImages/is/web-large/LC-N1514-back.jpg"}, {"label": "Object Number", "value": "48.101.1816"}, {"label": "Department", "value": "Islamic Art"}, {"label": "Accession Year", "value": "1948"}, {"label": "Country of origin", "value": "Iran"}, {"label": "Medium", "value": "Stucco; carved, painted"}, {"label": "Dimensions", "value": "L 4.5 x W 2.5 x H 1"}, {"label": "Classification", "value": "Stucco"}, {"label": "Credit", "value": "Rogers Fund, 1948"}], [{"isTitle": true, "value": "Stucco Fragment"}, {"label": "View item details", "isLink": true, "value": "http://www.metmuseum.org/art/collection/search/741334"}, {"isImage": true, "value": "https://images.metmuseum.org/CRDImages/is/web-large/LC-N1515-back.jpg"}, {"label": "Object Number", "value": "48.101.1817"}, {"label": "Department", "value": "Islamic Art"}, {"label": "Accession Year", "value": "1948"}, {"label": "Country of origin", "value": "Iran"}, {"label": "Medium", "value": "Stucco; carved, painted"}, {"label": "Dimensions", "value": "L 4.5 x W 3 x H 1.5"}, {"label": "Classification", "value": "Stucco"}, {"label": "Credit", "value": "Rogers Fund, 1948"}], [{"isTitle": true, "value": "Stucco Fragment"}, {"label": "View item details", "isLink": true, "value": "http://www.metmuseum.org/art/collection/search/741335"}, {"isImage": true, "value": "https://images.metmuseum.org/CRDImages/is/web-large/LC-N1516-back.jpg"}, {"label": "Object Number", "value": "48.101.1818"}, {"label": "Department", "value": "Islamic Art"}, {"label": "Accession Year", "value": "1948"}, {"label": "Country of origin", "value": "Iran"}, {"label": "Medium", "value": "Stucco; carved, painted"}, {"label": "Dimensions", "value": "L 4 x W 3 x H 1.5"}, {"label": "Classification", "value": "Stucco"}, {"label": "Credit", "value": "Rogers Fund, 1948"}], [{"isTitle": true, "value": "Stucco Fragment"}, {"label": "View item details", "isLink": true, "value": "http://www.metmuseum.org/art/collection/search/741336"}, {"isImage": true, "value": "https://images.metmuseum.org/CRDImages/is/web-large/LC-N1517-back.jpg"}, {"label": "Object Number", "value": "48.101.1819"}, {"label": "Department", "value": "Islamic Art"}, {"label": "Accession Year", "value": "1948"}, {"label": "Country of origin", "value": "Iran"}, {"label": "Medium", "value": "Stucco; carved, painted"}, {"label": "Dimensions", "value": "L 5 x W 3 x H 2"}, {"label": "Classification", "value": "Stucco"}, {"label": "Credit", "value": "Rogers Fund, 1948"}], [{"isTitle": true, "value": "Stucco Fragment"}, {"label": "View item details", "isLink": true, "value": "http://www.metmuseum.org/art/collection/search/741337"}, {"isImage": true, "value": "https://images.metmuseum.org/CRDImages/is/web-large/LC-N1518-back.jpg"}, {"label": "Object Number", "value": "48.101.1820"}, {"label": "Department", "value": "Islamic Art"}, {"label": "Accession Year", "value": "1948"}, {"label": "Country of origin", "value": "Iran"}, {"label": "Medium", "value": "Stucco; carved, painted"}, {"label": "Dimensions", "value": "L 5.5 x W 3.5 x H 1.5"}, {"label": "Classification", "value": "Stucco"}, {"label": "Credit", "value": "Rogers Fund, 1948"}], [{"isTitle": true, "value": "Stucco Fragment"}, {"label": "View item details", "isLink": true, "value": "http://www.metmuseum.org/art/collection/search/741338"}, {"isImage": true, "value": "https://images.metmuseum.org/CRDImages/is/web-large/LC-N1519-back.jpg"}, {"label": "Object Number", "value": "48.101.1821"}, {"label": "Department", "value": "Islamic Art"}, {"label": "Accession Year", "value": "1948"}, {"label": "Country of origin", "value": "Iran"}, {"label": "Medium", "value": "Stucco; carved, painted"}, {"label": "Dimensions", "value": "L 6 x W 4 x H 2"}, {"label": "Classification", "value": "Stucco"}, {"label": "Credit", "value": "Rogers Fund, 1948"}], [{"isTitle": true, "value": "Stucco Fragment"}, {"label": "View item details", "isLink": true, "value": "http://www.metmuseum.org/art/collection/search/741339"}, {"isImage": true, "value": "https://images.metmuseum.org/CRDImages/is/web-large/LC-N1520-back.jpg"}, {"label": "Object Number", "value": "48.101.1822"}, {"label": "Department", "value": "Islamic Art"}, {"label": "Accession Year", "value": "1948"}, {"label": "Country of origin", "value": "Iran"}, {"label": "Medium", "value": "Stucco; carved, painted"}, {"label": "Dimensions", "value": "L 6 x W 3 x H 1.5"}, {"label": "Classification", "value": "Stucco"}, {"label": "Credit", "value": "Rogers Fund, 1948"}]]